intezer_sdk/__init__.py
intezer_sdk/_account_api.py
intezer_sdk/_api.py
intezer_sdk/_endpoint_analysis_api.py
intezer_sdk/_operation.py
intezer_sdk/_util.py
intezer_sdk/account.py
intezer_sdk/alerts.py
intezer_sdk/alerts_results.py
intezer_sdk/analyses_history.py
intezer_sdk/analyses_results.py
intezer_sdk/analysis.py
intezer_sdk/api.py
intezer_sdk/base_analysis.py
intezer_sdk/consts.py
intezer_sdk/devices.py
intezer_sdk/devices_results.py
intezer_sdk/endpoint_analysis.py
intezer_sdk/errors.py
intezer_sdk/family.py
intezer_sdk/file.py
intezer_sdk/history_results.py
intezer_sdk/incidents.py
intezer_sdk/incidents_results.py
intezer_sdk/index.py
intezer_sdk/operation.py
intezer_sdk/sub_analysis.py
intezer_sdk/util.py
intezer_sdk-1.24.1.dist-info/licenses/LICENSE
intezer_sdk-1.24.1.dist-info/METADATA
intezer_sdk-1.24.1.dist-info/WHEEL
intezer_sdk-1.24.1.dist-info/top_level.txt
intezer_sdk-1.24.1.dist-info/RECORD
