Metadata-Version: 2.4
Name: intezer_sdk
Version: 1.24.1
Summary: Intezer Analyze SDK
Home-page: https://github.com/intezer/analyze-python-sdk
Author: Intezer Labs ltd.
Author-email: info@intezer.com
License: Apache 2.0
Keywords: intezer
Classifier: License :: OSI Approved :: Apache Software License
Classifier: Programming Language :: Python :: 3.9
Classifier: Programming Language :: Python :: 3.10
Classifier: Programming Language :: Python :: 3.11
Classifier: Programming Language :: Python :: 3.12
Classifier: Programming Language :: Python :: 3.13
Requires-Python: !=3.0.*,!=3.1.*,!=3.2.*,!=3.3.*,!=3.4.*,!=3.5.*,!=3.6.*,!=3.7.*,!=3.8.*
License-File: LICENSE
Requires-Dist: requests<3,>=2.29.0
Dynamic: author
Dynamic: author-email
Dynamic: classifier
Dynamic: description
Dynamic: description-content-type
Dynamic: home-page
Dynamic: keywords
Dynamic: license
Dynamic: license-file
Dynamic: requires-dist
Dynamic: requires-python
Dynamic: summary
